traffic_light_controller.v
module traffic_light_controller(input clk,
                                input rst,
                                output reg [1:0] NS_light, 
                                output reg [1:0] EW_light  
);

parameter S_0=3'b000;
parameter S_1=3'b001;
parameter S_2=3'b010;
parameter S_3=3'b011;
parameter S_4=3'b100;
parameter S_5=3'b101;

parameter RED=2'b00;
parameter YELLOW=2'b01;
parameter GREEN=2'b10;

reg [2:0] state;
integer count=0; 

always @(posedge clk or negedge rst) 
begin
    if(rst==1'b0)
    begin
        state<=S_0;
        NS_light<=GREEN;
        EW_light<=RED;   
    end
    else
    begin
        case(state)
        S_0:begin
            if(count=='d15)
            begin
                state<=S_1;
                NS_light<=YELLOW;
                EW_light<=RED;
                count<='d0;
            end
            else
            begin
                count<=count+1;
                state<=S_0;
            end
            end
        S_1:begin
            if(count=='d1)
            begin
                state<=S_2;
                NS_light<=RED;
                EW_light<=RED;
                count<='d0;
            end
            else
            begin
                count<=count+1;
                state<=S_1;
            end
            end
        S_2:begin
            if(count=='d1)
            begin
                state<=S_3;
                NS_light<=RED;
                EW_light<=GREEN;
                count<='d0;
            end
            else
            begin
                count<=count+1;
                state<=S_2;
            end
            end
        S_3:begin
            if(count=='d5)
            begin
                state<=S_4;
                NS_light<=YELLOW;
                EW_light<=RED;
                count<='d0;
            end
            else
            begin
                count<=count+1;
                state<=S_3;
            end
            end
        S_4:begin
            if(count=='d1)
            begin
                state<=S_5;
                NS_light<=RED;
                EW_light<=YELLOW;
                count<='d0;
            end
            else
            begin
                count<=count+1; 
                state<=S_4;
            end
            end
        S_5:begin
            if(count=='d1)
            begin
                state<=S_0;
                NS_light<=RED;
                EW_light<=RED;
                count<='d0;
            end
            else
            begin
                count<=count+1;
                state<=S_5;
            end
            end
        default:begin
                count=0;
                state<=S_0;
                NS_light<=GREEN; 
                EW_light<=RED; 
                end    
        endcase 
    end
end

endmodule

traffic_light_controller_test.v
`include "traffic_light_controller.v"
module traffic_light_controller_test;
//Inputs
reg clk;
reg rst;

//Outputs
wire [1:0] NS_light;
wire [1:0] EW_light;
//Instantiate the Unit Under Test
traffic_light_controller uut(
    .clk(clk),
    .rst(rst),
    .NS_light(NS_light),
    .EW_light(EW_light)
);

always #3 clk=~clk;
initial begin

    $dumpfile("traffic_light_controller_test.vcd");
    $dumpvars(0,traffic_light_controller_test);

    //Initialize Inputs

    clk=0;rst=0;

    //Wait for 10 ns for global reset to finish

    #10 rst=1;
    #200;
    //$stop();
    $finish();
    
    //Add stimulus here

end

endmodule

traffic_light_controller_test.vcd
$date
	Mon Jul 25 20:18:27 2022
$end
$version
	Icarus Verilog
$end
$timescale
	1s
$end
$scope module traffic_light_controller_test $end
$var wire 2 ! EW_light [1:0] $end
$var wire 2 " NS_light [1:0] $end
$var reg 1 # clk $end
$var reg 1 $ rst $end
$scope module uut $end
$var wire 1 % clk $end
$var wire 1 & rst $end
$var reg 2 ' EW_light [1:0] $end
$var reg 2 ( NS_light [1:0] $end
$var integer 32 ) count [31:0] $end
$var reg 3 * state [2:0] $end
$upscope $end
$upscope $end
$enddefinitions $end
#0
$dumpvars
b0 *
b0 )
b10 (
b0 '
0&
0%
0$
0#
b10 "
b0 !
$end
#3
1#
1%
#6
0#
0%
#9
1#
1%
#10
1$
1&
#12
0#
0%
#15
b1 )
1#
1%
#18
0#
0%
#21
b10 )
1#
1%
#24
0#
0%
#27
b11 )
1#
1%
#30
0#
0%
#33
b100 )
1#
1%
#36
0#
0%
#39
b101 )
1#
1%
#42
0#
0%
#45
b110 )
1#
1%
#48
0#
0%
#51
b111 )
1#
1%
#54
0#
0%
#57
b1000 )
1#
1%
#60
0#
0%
#63
b1001 )
1#
1%
#66
0#
0%
#69
b1010 )
1#
1%
#72
0#
0%
#75
b1011 )
1#
1%
#78
0#
0%
#81
b1100 )
1#
1%
#84
0#
0%
#87
b1101 )
1#
1%
#90
0#
0%
#93
b1110 )
1#
1%
#96
0#
0%
#99
b1111 )
1#
1%
#102
0#
0%
#105
b0 )
b1 (
b1 "
b1 *
1#
1%
#108
0#
0%
#111
b1 )
1#
1%
#114
0#
0%
#117
b0 )
b0 (
b0 "
b10 *
1#
1%
#120
0#
0%
#123
b1 )
1#
1%
#126
0#
0%
#129
b0 )
b10 '
b10 !
b11 *
1#
1%
#132
0#
0%
#135
b1 )
1#
1%
#138
0#
0%
#141
b10 )
1#
1%
#144
0#
0%
#147
b11 )
1#
1%
#150
0#
0%
#153
b100 )
1#
1%
#156
0#
0%
#159
b101 )
1#
1%
#162
0#
0%
#165
b0 )
b0 '
b0 !
b1 (
b1 "
b100 *
1#
1%
#168
0#
0%
#171
b1 )
1#
1%
#174
0#
0%
#177
b0 )
b1 '
b1 !
b0 (
b0 "
b101 *
1#
1%
#180
0#
0%
#183
b1 )
1#
1%
#186
0#
0%
#189
b0 )
b0 '
b0 !
b0 *
1#
1%
#192
0#
0%
#195
b1 )
1#
1%
#198
0#
0%
#201
b10 )
1#
1%
#204
0#
0%
#207
b11 )
1#
1%
